yivo/__init__.py
yivo/gen/msg_parts.py
yivo/gen/templates/msg.c.jinja
yivo/gen/templates/msg.h.jinja
yivo/gen/templates/msg.py.jinja
yivo/gen/tokenize.py
yivo/gen/yivogen.py
yivo/packet.py
yivo/parser.py
yivo-2025.8.23.1.dist-info/METADATA
yivo-2025.8.23.1.dist-info/WHEEL
yivo-2025.8.23.1.dist-info/entry_points.txt
yivo-2025.8.23.1.dist-info/RECORD
