Metadata-Version: 2.3
Name: yivo
Version: 2025.8.23.1
Summary: Message serialization
License: MIT
Keywords: arduino
Author: walchko
Author-email: walchko@users.noreply.github.com
Requires-Python: >=3.10
Classifier: Development Status :: 4 - Beta
Classifier: Intended Audience :: Developers
Classifier: License :: OSI Approved :: MIT License
Classifier: Operating System :: OS Independent
Classifier: Programming Language :: Python :: 3
Classifier: Programming Language :: Python :: 3.10
Classifier: Programming Language :: Python :: 3.11
Classifier: Programming Language :: Python :: 3.12
Classifier: Programming Language :: Python :: 3.13
Classifier: Topic :: Software Development :: Libraries
Classifier: Topic :: Software Development :: Libraries :: Application Frameworks
Classifier: Topic :: Software Development :: Libraries :: Python Modules
Requires-Dist: colorama
Requires-Dist: jinja2
Project-URL: Homepage, https://pypi.org/project/yivo/
Project-URL: Repository, http://github.com/MomsFriendlyRobotCompany/yivo
